vectorboard/__initi__.py
vectorboard/experiment.py
vectorboard/search.py
vectorboard-0.0.1.dist-info/LICENSE
vectorboard-0.0.1.dist-info/METADATA
vectorboard-0.0.1.dist-info/WHEEL
vectorboard-0.0.1.dist-info/RECORD
