Metadata-Version: 2.1
Name: vectorboard
Version: 0.0.1
Summary: Hyperparameter optimisation for your LLM Emebddings.
Author: Hamed Mohammadpour
Author-email: HamedMP@users.noreply.github.com
Requires-Python: >=3.10,<4.0
Classifier: Programming Language :: Python :: 3
Classifier: Programming Language :: Python :: 3.10
Classifier: Programming Language :: Python :: 3.11
Requires-Dist: gradio (>=3.4,<4.0)
Requires-Dist: langchain (>=0.0.300,<0.0.301)
Requires-Dist: matplotlib (>=3.4,<4.0)
Requires-Dist: pandas (>=1.3,<2.0)
Requires-Dist: rich (>=13.5.3,<14.0.0)
